{
  "db_name": "SQLite",
  "query": "SELECT  graph_id as \"graph_id:Uuid \", instance_id  as \"instance_id:Uuid \", graph_ipfs_base_url, pegin_txid, amount, status, challenge_txid,disprove_txid, created_at as \"created_at: i64\" FROM graph WHERE  graph_id = ?",
  "describe": {
    "columns": [
      {
        "name": "graph_id:Uuid ",
        "ordinal": 0,
        "type_info": "Text"
      },
      {
        "name": "instance_id:Uuid ",
        "ordinal": 1,
        "type_info": "Text"
      },
      {
        "name": "graph_ipfs_base_url",
        "ordinal": 2,
        "type_info": "Text"
      },
      {
        "name": "pegin_txid",
        "ordinal": 3,
        "type_info": "Text"
      },
      {
        "name": "amount",
        "ordinal": 4,
        "type_info": "Integer"
      },
      {
        "name": "status",
        "ordinal": 5,
        "type_info": "Text"
      },
      {
        "name": "challenge_txid",
        "ordinal": 6,
        "type_info": "Text"
      },
      {
        "name": "disprove_txid",
        "ordinal": 7,
        "type_info": "Text"
      },
      {
        "name": "created_at: i64",
        "ordinal": 8,
        "type_info": "Datetime"
      }
    ],
    "parameters": {
      "Right": 1
    },
    "nullable": [
      false,
      false,
      false,
      false,
      false,
      false,
      true,
      true,
      false
    ]
  },
  "hash": "0642b6f4df6a7789493a0a684b81a314b2d502eee56694ed604bdf1fdd266d39"
}
